<?xml version="1.0" encoding="UTF-8" standalone="yes"?>
<w:document xmlns:wpc="http://schemas.microsoft.com/office/word/2010/wordprocessingCanvas" xmlns:cx="http://schemas.microsoft.com/office/drawing/2014/chartex" xmlns:cx1="http://schemas.microsoft.com/office/drawing/2015/9/8/chartex" xmlns:cx2="http://schemas.microsoft.com/office/drawing/2015/10/21/chartex" xmlns:cx3="http://schemas.microsoft.com/office/drawing/2016/5/9/chartex" xmlns:cx4="http://schemas.microsoft.com/office/drawing/2016/5/10/chartex" xmlns:cx5="http://schemas.microsoft.com/office/drawing/2016/5/11/chartex" xmlns:cx6="http://schemas.microsoft.com/office/drawing/2016/5/12/chartex" xmlns:cx7="http://schemas.microsoft.com/office/drawing/2016/5/13/chartex" xmlns:cx8="http://schemas.microsoft.com/office/drawing/2016/5/14/chartex" xmlns:mc="http://schemas.openxmlformats.org/markup-compatibility/2006" xmlns:aink="http://schemas.microsoft.com/office/drawing/2016/ink" xmlns:am3d="http://schemas.microsoft.com/office/drawing/2017/model3d" xmlns:o="urn:schemas-microsoft-com:office:office" xmlns:oel="http://schemas.microsoft.com/office/2019/extlst" xmlns:r="http://schemas.openxmlformats.org/officeDocument/2006/relationships" xmlns:m="http://schemas.openxmlformats.org/officeDocument/2006/math" xmlns:v="urn:schemas-microsoft-com:vml" xmlns:wp14="http://schemas.microsoft.com/office/word/2010/wordprocessingDrawing" xmlns:wp="http://schemas.openxmlformats.org/drawingml/2006/wordprocessingDrawing" xmlns:w10="urn:schemas-microsoft-com:office:word" xmlns:w="http://schemas.openxmlformats.org/wordprocessingml/2006/main" xmlns:w14="http://schemas.microsoft.com/office/word/2010/wordml" xmlns:w15="http://schemas.microsoft.com/office/word/2012/wordml" xmlns:w16cex="http://schemas.microsoft.com/office/word/2018/wordml/cex" xmlns:w16cid="http://schemas.microsoft.com/office/word/2016/wordml/cid" xmlns:w16="http://schemas.microsoft.com/office/word/2018/wordml" xmlns:w16du="http://schemas.microsoft.com/office/word/2023/wordml/word16du" xmlns:w16sdtdh="http://schemas.microsoft.com/office/word/2020/wordml/sdtdatahash" xmlns:w16sdtfl="http://schemas.microsoft.com/office/word/2024/wordml/sdtformatlock" xmlns:w16se="http://schemas.microsoft.com/office/word/2015/wordml/symex" xmlns:wpg="http://schemas.microsoft.com/office/word/2010/wordprocessingGroup" xmlns:wpi="http://schemas.microsoft.com/office/word/2010/wordprocessingInk" xmlns:wne="http://schemas.microsoft.com/office/word/2006/wordml" xmlns:wps="http://schemas.microsoft.com/office/word/2010/wordprocessingShape" mc:Ignorable="w14 w15 w16se w16cid w16 w16cex w16sdtdh w16sdtfl w16du wp14"><w:body><w:p w14:paraId="6BE9EFB1" w14:textId="77777777" w:rsidR="00D5346D" w:rsidRPr="00D5346D" w:rsidRDefault="00D5346D" w:rsidP="00D5346D"><w:pPr><w:rPr><w:b/><w:bCs/></w:rPr></w:pPr><w:r w:rsidRPr="00D5346D"><w:rPr><w:b/><w:bCs/></w:rPr><w:t>LOAN AGREEMENT AND TERMS &amp; CONDITIONS</w:t></w:r></w:p><w:p w14:paraId="089D5B88" w14:textId="77777777" w:rsidR="00D5346D" w:rsidRPr="00D5346D" w:rsidRDefault="00D5346D" w:rsidP="00D5346D"><w:r w:rsidRPr="00D5346D"><w:rPr><w:b/><w:bCs/></w:rPr><w:t>Lenni (Pty) Ltd</w:t></w:r></w:p><w:p w14:paraId="17CD1832" w14:textId="77777777" w:rsidR="00D5346D" w:rsidRPr="00D5346D" w:rsidRDefault="00000000" w:rsidP="00D5346D"><w:r><w:pict w14:anchorId="78770F2F"><v:rect id="_x0000_i1025" style="width:0;height:1.5pt" o:hralign="center" o:hrstd="t" o:hr="t" fillcolor="#a0a0a0" stroked="f"/></w:pict></w:r></w:p><w:p w14:paraId="3225FAF3" w14:textId="77777777" w:rsidR="00D5346D" w:rsidRPr="00D5346D" w:rsidRDefault="00D5346D" w:rsidP="00D5346D"><w:pPr><w:rPr><w:b/><w:bCs/></w:rPr></w:pPr><w:r w:rsidRPr="00D5346D"><w:rPr><w:b/><w:bCs/></w:rPr><w:t>1. INTRODUCTION</w:t></w:r></w:p><w:p w14:paraId="76190C5F" w14:textId="77777777" w:rsidR="00D5346D" w:rsidRPr="00D5346D" w:rsidRDefault="00D5346D" w:rsidP="00D5346D"><w:r w:rsidRPr="00D5346D"><w:t xml:space="preserve">This Agreement governs the loan entered into between </w:t></w:r><w:r w:rsidRPr="00D5346D"><w:rPr><w:b/><w:bCs/></w:rPr><w:t>Lenni (Pty) Ltd</w:t></w:r><w:r w:rsidRPr="00D5346D"><w:t xml:space="preserve"> (“the Credit Provider”) and the Applicant (“the Borrower”).</w:t></w:r></w:p><w:p w14:paraId="39FC9F62" w14:textId="77777777" w:rsidR="00D5346D" w:rsidRPr="00D5346D" w:rsidRDefault="00D5346D" w:rsidP="00D5346D"><w:r w:rsidRPr="00D5346D"><w:t>By accepting this Agreement electronically or otherwise, the Applicant confirms that they have read, understood, and agreed to all terms and conditions contained herein.</w:t></w:r></w:p><w:p w14:paraId="2B7B4AA5" w14:textId="77777777" w:rsidR="00D5346D" w:rsidRPr="00D5346D" w:rsidRDefault="00000000" w:rsidP="00D5346D"><w:r><w:pict w14:anchorId="0A8E7896"><v:rect id="_x0000_i1026" style="width:0;height:1.5pt" o:hralign="center" o:hrstd="t" o:hr="t" fillcolor="#a0a0a0" stroked="f"/></w:pict></w:r></w:p><w:p w14:paraId="33EB5FD4" w14:textId="77777777" w:rsidR="00D5346D" w:rsidRPr="00D5346D" w:rsidRDefault="00D5346D" w:rsidP="00D5346D"><w:pPr><w:rPr><w:b/><w:bCs/></w:rPr></w:pPr><w:r w:rsidRPr="00D5346D"><w:rPr><w:b/><w:bCs/></w:rPr><w:t>2. LOAN APPLICATION AND ACCEPTANCE</w:t></w:r></w:p><w:p w14:paraId="67C81138" w14:textId="77777777" w:rsidR="00D5346D" w:rsidRPr="00D5346D" w:rsidRDefault="00D5346D" w:rsidP="00D5346D"><w:r w:rsidRPr="00D5346D"><w:t>2.1 The Applicant applies for a loan in the language of their choice via the Credit Provider’s Loan Management System (LMS), website, or mobile application.</w:t></w:r></w:p><w:p w14:paraId="01497CF2" w14:textId="77777777" w:rsidR="00D5346D" w:rsidRPr="00D5346D" w:rsidRDefault="00D5346D" w:rsidP="00D5346D"><w:r w:rsidRPr="00D5346D"><w:t>2.2 Approval of the loan remains at the sole discretion of the Credit Provider, subject to affordability assessment and verification.</w:t></w:r></w:p><w:p w14:paraId="7B4AFD18" w14:textId="77777777" w:rsidR="00D5346D" w:rsidRPr="00D5346D" w:rsidRDefault="00D5346D" w:rsidP="00D5346D"><w:r w:rsidRPr="00D5346D"><w:t>2.3 Upon approval, the loan amount (or net proceeds after settlement of any existing loan) will be paid into the Applicant’s nominated bank account.</w:t></w:r></w:p><w:p w14:paraId="06DC6FDE" w14:textId="77777777" w:rsidR="00D5346D" w:rsidRPr="00D5346D" w:rsidRDefault="00000000" w:rsidP="00D5346D"><w:r><w:pict w14:anchorId="16B4C55F"><v:rect id="_x0000_i1027" style="width:0;height:1.5pt" o:hralign="center" o:hrstd="t" o:hr="t" fillcolor="#a0a0a0" stroked="f"/></w:pict></w:r></w:p><w:p w14:paraId="51BC571D" w14:textId="77777777" w:rsidR="00D5346D" w:rsidRPr="00D5346D" w:rsidRDefault="00D5346D" w:rsidP="00D5346D"><w:pPr><w:rPr><w:b/><w:bCs/></w:rPr></w:pPr><w:r w:rsidRPr="00D5346D"><w:rPr><w:b/><w:bCs/></w:rPr><w:t>3. REPAYMENT AUTHORISATION (PAYROLL DEDUCTION)</w:t></w:r></w:p><w:p w14:paraId="4166C79B" w14:textId="77777777" w:rsidR="00D5346D" w:rsidRPr="00D5346D" w:rsidRDefault="00D5346D" w:rsidP="00D5346D"><w:r w:rsidRPr="00D5346D"><w:t>3.1 The Applicant irrevocably authorises their Employer to deduct agreed repayment amounts (monthly, fortnightly, or weekly) from their salary until the loan is fully settled.</w:t></w:r></w:p><w:p w14:paraId="1F045782" w14:textId="77777777" w:rsidR="00D5346D" w:rsidRPr="00D5346D" w:rsidRDefault="00D5346D" w:rsidP="00D5346D"><w:r w:rsidRPr="00D5346D"><w:t>3.2 The Applicant consents that:</w:t></w:r></w:p><w:p w14:paraId="049DD3AC" w14:textId="77777777" w:rsidR="00D5346D" w:rsidRPr="00D5346D" w:rsidRDefault="00D5346D" w:rsidP="00D5346D"><w:pPr><w:numPr><w:ilvl w:val="0"/><w:numId w:val="1"/></w:numPr></w:pPr><w:r w:rsidRPr="00D5346D"><w:t>Deductions will continue until all obligations are settled</w:t></w:r></w:p><w:p w14:paraId="35CE1EDD" w14:textId="77777777" w:rsidR="00D5346D" w:rsidRPr="00D5346D" w:rsidRDefault="00D5346D" w:rsidP="00D5346D"><w:pPr><w:numPr><w:ilvl w:val="0"/><w:numId w:val="1"/></w:numPr></w:pPr><w:r w:rsidRPr="00D5346D"><w:t>The Employer may deduct the full outstanding balance from final salary or any amounts due upon termination of employment</w:t></w:r></w:p><w:p w14:paraId="3F82D2A9" w14:textId="77777777" w:rsidR="00D5346D" w:rsidRPr="00D5346D" w:rsidRDefault="00D5346D" w:rsidP="00D5346D"><w:r w:rsidRPr="00D5346D"><w:t>3.3 The Applicant authorises the Employer to share relevant employment and payroll information with the Credit Provider where reasonably required.</w:t></w:r></w:p><w:p w14:paraId="18D87716" w14:textId="77777777" w:rsidR="00D5346D" w:rsidRPr="00D5346D" w:rsidRDefault="00000000" w:rsidP="00D5346D"><w:r><w:pict w14:anchorId="30048DCD"><v:rect id="_x0000_i1028" style="width:0;height:1.5pt" o:hralign="center" o:hrstd="t" o:hr="t" fillcolor="#a0a0a0" stroked="f"/></w:pict></w:r></w:p><w:p w14:paraId="435D4ABA" w14:textId="77777777" w:rsidR="00D5346D" w:rsidRPr="00D5346D" w:rsidRDefault="00D5346D" w:rsidP="00D5346D"><w:pPr><w:rPr><w:b/><w:bCs/></w:rPr></w:pPr><w:r w:rsidRPr="00D5346D"><w:rPr><w:b/><w:bCs/></w:rPr><w:t>4. DEBIT ORDER AUTHORISATION (NAEDO)</w:t></w:r></w:p><w:p w14:paraId="6D08A333" w14:textId="77777777" w:rsidR="00D5346D" w:rsidRPr="00D5346D" w:rsidRDefault="00D5346D" w:rsidP="00D5346D"><w:r w:rsidRPr="00D5346D"><w:t>4.1 The Applicant authorises the Credit Provider to issue debit instructions against their bank account via NAEDO in the event that:</w:t></w:r></w:p><w:p w14:paraId="7F69CF5D" w14:textId="77777777" w:rsidR="00D5346D" w:rsidRPr="00D5346D" w:rsidRDefault="00D5346D" w:rsidP="00D5346D"><w:pPr><w:numPr><w:ilvl w:val="0"/><w:numId w:val="2"/></w:numPr></w:pPr><w:r w:rsidRPr="00D5346D"><w:t>Payroll deductions fail, or</w:t></w:r></w:p><w:p w14:paraId="19451C19" w14:textId="77777777" w:rsidR="00D5346D" w:rsidRPr="00D5346D" w:rsidRDefault="00D5346D" w:rsidP="00D5346D"><w:pPr><w:numPr><w:ilvl w:val="0"/><w:numId w:val="2"/></w:numPr></w:pPr><w:r w:rsidRPr="00D5346D"><w:lastRenderedPageBreak/><w:t>Employment is terminated</w:t></w:r></w:p><w:p w14:paraId="0B53A18F" w14:textId="77777777" w:rsidR="00D5346D" w:rsidRPr="00D5346D" w:rsidRDefault="00D5346D" w:rsidP="00D5346D"><w:r w:rsidRPr="00D5346D"><w:t>4.2 The Applicant acknowledges:</w:t></w:r></w:p><w:p w14:paraId="2269A073" w14:textId="77777777" w:rsidR="00D5346D" w:rsidRPr="00D5346D" w:rsidRDefault="00D5346D" w:rsidP="00D5346D"><w:pPr><w:numPr><w:ilvl w:val="0"/><w:numId w:val="3"/></w:numPr></w:pPr><w:r w:rsidRPr="00D5346D"><w:t>Debit orders may be processed on or near salary dates</w:t></w:r></w:p><w:p w14:paraId="493D29C7" w14:textId="77777777" w:rsidR="00D5346D" w:rsidRPr="00D5346D" w:rsidRDefault="00D5346D" w:rsidP="00D5346D"><w:pPr><w:numPr><w:ilvl w:val="0"/><w:numId w:val="3"/></w:numPr></w:pPr><w:r w:rsidRPr="00D5346D"><w:t>Multiple debit attempts may be made for unpaid instalments</w:t></w:r></w:p><w:p w14:paraId="4A789481" w14:textId="77777777" w:rsidR="00D5346D" w:rsidRPr="00D5346D" w:rsidRDefault="00D5346D" w:rsidP="00D5346D"><w:pPr><w:numPr><w:ilvl w:val="0"/><w:numId w:val="3"/></w:numPr></w:pPr><w:r w:rsidRPr="00D5346D"><w:t>Bank charges may be incurred for debit instructions</w:t></w:r></w:p><w:p w14:paraId="0EE5F135" w14:textId="77777777" w:rsidR="00D5346D" w:rsidRPr="00D5346D" w:rsidRDefault="00D5346D" w:rsidP="00D5346D"><w:r w:rsidRPr="00D5346D"><w:t>4.3 The Applicant consents to NAEDO tracking functionality for payment collection and tracing purposes.</w:t></w:r></w:p><w:p w14:paraId="266337A7" w14:textId="77777777" w:rsidR="00D5346D" w:rsidRPr="00D5346D" w:rsidRDefault="00000000" w:rsidP="00D5346D"><w:r><w:pict w14:anchorId="39C0C578"><v:rect id="_x0000_i1029" style="width:0;height:1.5pt" o:hralign="center" o:hrstd="t" o:hr="t" fillcolor="#a0a0a0" stroked="f"/></w:pict></w:r></w:p><w:p w14:paraId="475ABA63" w14:textId="77777777" w:rsidR="00D5346D" w:rsidRPr="00D5346D" w:rsidRDefault="00D5346D" w:rsidP="00D5346D"><w:pPr><w:rPr><w:b/><w:bCs/></w:rPr></w:pPr><w:r w:rsidRPr="00D5346D"><w:rPr><w:b/><w:bCs/></w:rPr><w:t>5. COST OF CREDIT ACKNOWLEDGEMENT</w:t></w:r></w:p><w:p w14:paraId="7EAD550F" w14:textId="77777777" w:rsidR="00D5346D" w:rsidRPr="00D5346D" w:rsidRDefault="00D5346D" w:rsidP="00D5346D"><w:r w:rsidRPr="00D5346D"><w:t>5.1 The Applicant confirms that prior to entering into this Agreement, they were provided with a quotation detailing:</w:t></w:r></w:p><w:p w14:paraId="5AA50C45" w14:textId="77777777" w:rsidR="00D5346D" w:rsidRPr="00D5346D" w:rsidRDefault="00D5346D" w:rsidP="00D5346D"><w:pPr><w:numPr><w:ilvl w:val="0"/><w:numId w:val="4"/></w:numPr></w:pPr><w:r w:rsidRPr="00D5346D"><w:t>Loan amount</w:t></w:r></w:p><w:p w14:paraId="08D49B98" w14:textId="77777777" w:rsidR="00D5346D" w:rsidRPr="00D5346D" w:rsidRDefault="00D5346D" w:rsidP="00D5346D"><w:pPr><w:numPr><w:ilvl w:val="0"/><w:numId w:val="4"/></w:numPr></w:pPr><w:r w:rsidRPr="00D5346D"><w:t>Interest rate</w:t></w:r></w:p><w:p w14:paraId="5F61D89B" w14:textId="77777777" w:rsidR="00D5346D" w:rsidRPr="00D5346D" w:rsidRDefault="00D5346D" w:rsidP="00D5346D"><w:pPr><w:numPr><w:ilvl w:val="0"/><w:numId w:val="4"/></w:numPr></w:pPr><w:r w:rsidRPr="00D5346D"><w:t>Initiation fee</w:t></w:r></w:p><w:p w14:paraId="47BF899A" w14:textId="77777777" w:rsidR="00D5346D" w:rsidRPr="00D5346D" w:rsidRDefault="00D5346D" w:rsidP="00D5346D"><w:pPr><w:numPr><w:ilvl w:val="0"/><w:numId w:val="4"/></w:numPr></w:pPr><w:r w:rsidRPr="00D5346D"><w:t>Service fee</w:t></w:r></w:p><w:p w14:paraId="1A0EA3E0" w14:textId="77777777" w:rsidR="00D5346D" w:rsidRPr="00D5346D" w:rsidRDefault="00D5346D" w:rsidP="00D5346D"><w:pPr><w:numPr><w:ilvl w:val="0"/><w:numId w:val="4"/></w:numPr></w:pPr><w:r w:rsidRPr="00D5346D"><w:t>Total repayment amount</w:t></w:r></w:p><w:p w14:paraId="3EB1946D" w14:textId="77777777" w:rsidR="00D5346D" w:rsidRPr="00D5346D" w:rsidRDefault="00D5346D" w:rsidP="00D5346D"><w:r w:rsidRPr="00D5346D"><w:t>5.2 The Applicant acknowledges and accepts the full cost of credit.</w:t></w:r></w:p><w:p w14:paraId="3D980173" w14:textId="77777777" w:rsidR="00D5346D" w:rsidRPr="00D5346D" w:rsidRDefault="00000000" w:rsidP="00D5346D"><w:r><w:pict w14:anchorId="336457D3"><v:rect id="_x0000_i1030" style="width:0;height:1.5pt" o:hralign="center" o:hrstd="t" o:hr="t" fillcolor="#a0a0a0" stroked="f"/></w:pict></w:r></w:p><w:p w14:paraId="0B7C692E" w14:textId="77777777" w:rsidR="00D5346D" w:rsidRPr="00D5346D" w:rsidRDefault="00D5346D" w:rsidP="00D5346D"><w:pPr><w:rPr><w:b/><w:bCs/></w:rPr></w:pPr><w:r w:rsidRPr="00D5346D"><w:rPr><w:b/><w:bCs/></w:rPr><w:t>6. AFFORDABILITY AND DECLARATION</w:t></w:r></w:p><w:p w14:paraId="3EDBB95E" w14:textId="77777777" w:rsidR="00D5346D" w:rsidRPr="00D5346D" w:rsidRDefault="00D5346D" w:rsidP="00D5346D"><w:r w:rsidRPr="00D5346D"><w:t>6.1 The Applicant declares that:</w:t></w:r></w:p><w:p w14:paraId="0E6312B5" w14:textId="77777777" w:rsidR="00D5346D" w:rsidRPr="00D5346D" w:rsidRDefault="00D5346D" w:rsidP="00D5346D"><w:pPr><w:numPr><w:ilvl w:val="0"/><w:numId w:val="5"/></w:numPr></w:pPr><w:r w:rsidRPr="00D5346D"><w:t>All information provided is true, accurate, and complete</w:t></w:r></w:p><w:p w14:paraId="09D16F24" w14:textId="77777777" w:rsidR="00D5346D" w:rsidRPr="00D5346D" w:rsidRDefault="00D5346D" w:rsidP="00D5346D"><w:pPr><w:numPr><w:ilvl w:val="0"/><w:numId w:val="5"/></w:numPr></w:pPr><w:r w:rsidRPr="00D5346D"><w:t>They can afford the repayments without becoming over-indebted</w:t></w:r></w:p><w:p w14:paraId="42A17332" w14:textId="77777777" w:rsidR="00D5346D" w:rsidRPr="00D5346D" w:rsidRDefault="00D5346D" w:rsidP="00D5346D"><w:r w:rsidRPr="00D5346D"><w:t>6.2 The Applicant acknowledges that providing false or misleading information constitutes a breach of this Agreement.</w:t></w:r></w:p><w:p w14:paraId="46CD2B11" w14:textId="77777777" w:rsidR="00D5346D" w:rsidRPr="00D5346D" w:rsidRDefault="00000000" w:rsidP="00D5346D"><w:r><w:pict w14:anchorId="2B89FB37"><v:rect id="_x0000_i1031" style="width:0;height:1.5pt" o:hralign="center" o:hrstd="t" o:hr="t" fillcolor="#a0a0a0" stroked="f"/></w:pict></w:r></w:p><w:p w14:paraId="47FA0637" w14:textId="77777777" w:rsidR="00D5346D" w:rsidRPr="00D5346D" w:rsidRDefault="00D5346D" w:rsidP="00D5346D"><w:pPr><w:rPr><w:b/><w:bCs/></w:rPr></w:pPr><w:r w:rsidRPr="00D5346D"><w:rPr><w:b/><w:bCs/></w:rPr><w:t>7. CREDIT BUREAU CONSENT</w:t></w:r></w:p><w:p w14:paraId="5DCD3A0E" w14:textId="77777777" w:rsidR="00D5346D" w:rsidRPr="00D5346D" w:rsidRDefault="00D5346D" w:rsidP="00D5346D"><w:r w:rsidRPr="00D5346D"><w:t>7.1 The Applicant consents to the Credit Provider:</w:t></w:r></w:p><w:p w14:paraId="25390F44" w14:textId="77777777" w:rsidR="00D5346D" w:rsidRPr="00D5346D" w:rsidRDefault="00D5346D" w:rsidP="00D5346D"><w:pPr><w:numPr><w:ilvl w:val="0"/><w:numId w:val="6"/></w:numPr></w:pPr><w:r w:rsidRPr="00D5346D"><w:t>Accessing their credit profile from registered credit bureaus</w:t></w:r></w:p><w:p w14:paraId="190B77ED" w14:textId="77777777" w:rsidR="00D5346D" w:rsidRPr="00D5346D" w:rsidRDefault="00D5346D" w:rsidP="00D5346D"><w:pPr><w:numPr><w:ilvl w:val="0"/><w:numId w:val="6"/></w:numPr></w:pPr><w:r w:rsidRPr="00D5346D"><w:t>Reporting the loan and repayment behaviour to such bureaus</w:t></w:r></w:p><w:p w14:paraId="680478DE" w14:textId="77777777" w:rsidR="00D5346D" w:rsidRPr="00D5346D" w:rsidRDefault="00000000" w:rsidP="00D5346D"><w:r><w:lastRenderedPageBreak/><w:pict w14:anchorId="67774458"><v:rect id="_x0000_i1032" style="width:0;height:1.5pt" o:hralign="center" o:hrstd="t" o:hr="t" fillcolor="#a0a0a0" stroked="f"/></w:pict></w:r></w:p><w:p w14:paraId="0E9DB837" w14:textId="77777777" w:rsidR="00D5346D" w:rsidRPr="00D5346D" w:rsidRDefault="00D5346D" w:rsidP="00D5346D"><w:pPr><w:rPr><w:b/><w:bCs/></w:rPr></w:pPr><w:r w:rsidRPr="00D5346D"><w:rPr><w:b/><w:bCs/></w:rPr><w:t>8. POPIA CONSENT (PROTECTION OF PERSONAL INFORMATION)</w:t></w:r></w:p><w:p w14:paraId="53B0C81B" w14:textId="77777777" w:rsidR="00D5346D" w:rsidRPr="00D5346D" w:rsidRDefault="00D5346D" w:rsidP="00D5346D"><w:r w:rsidRPr="00D5346D"><w:t>8.1 The Applicant consents to the collection, processing, storage, and sharing of their personal information in accordance with applicable data protection laws.</w:t></w:r></w:p><w:p w14:paraId="3FF9A181" w14:textId="77777777" w:rsidR="00D5346D" w:rsidRPr="00D5346D" w:rsidRDefault="00D5346D" w:rsidP="00D5346D"><w:r w:rsidRPr="00D5346D"><w:t>8.2 Personal information may be used for:</w:t></w:r></w:p><w:p w14:paraId="66B5A8B4" w14:textId="77777777" w:rsidR="00D5346D" w:rsidRPr="00D5346D" w:rsidRDefault="00D5346D" w:rsidP="00D5346D"><w:pPr><w:numPr><w:ilvl w:val="0"/><w:numId w:val="7"/></w:numPr></w:pPr><w:r w:rsidRPr="00D5346D"><w:t>Credit assessment and affordability checks</w:t></w:r></w:p><w:p w14:paraId="6215EF3C" w14:textId="77777777" w:rsidR="00D5346D" w:rsidRPr="00D5346D" w:rsidRDefault="00D5346D" w:rsidP="00D5346D"><w:pPr><w:numPr><w:ilvl w:val="0"/><w:numId w:val="7"/></w:numPr></w:pPr><w:r w:rsidRPr="00D5346D"><w:t>Account management and administration</w:t></w:r></w:p><w:p w14:paraId="7E87B592" w14:textId="77777777" w:rsidR="00D5346D" w:rsidRPr="00D5346D" w:rsidRDefault="00D5346D" w:rsidP="00D5346D"><w:pPr><w:numPr><w:ilvl w:val="0"/><w:numId w:val="7"/></w:numPr></w:pPr><w:r w:rsidRPr="00D5346D"><w:t>Payment processing and collections</w:t></w:r></w:p><w:p w14:paraId="374DAE02" w14:textId="77777777" w:rsidR="00D5346D" w:rsidRPr="00D5346D" w:rsidRDefault="00D5346D" w:rsidP="00D5346D"><w:pPr><w:numPr><w:ilvl w:val="0"/><w:numId w:val="7"/></w:numPr></w:pPr><w:r w:rsidRPr="00D5346D"><w:t>Legal and regulatory compliance</w:t></w:r></w:p><w:p w14:paraId="3A1941E4" w14:textId="77777777" w:rsidR="00D5346D" w:rsidRPr="00D5346D" w:rsidRDefault="00D5346D" w:rsidP="00D5346D"><w:r w:rsidRPr="00D5346D"><w:t>8.3 Personal information may be shared with:</w:t></w:r></w:p><w:p w14:paraId="7601A662" w14:textId="77777777" w:rsidR="00D5346D" w:rsidRPr="00D5346D" w:rsidRDefault="00D5346D" w:rsidP="00D5346D"><w:pPr><w:numPr><w:ilvl w:val="0"/><w:numId w:val="8"/></w:numPr></w:pPr><w:r w:rsidRPr="00D5346D"><w:t>Credit bureaus</w:t></w:r></w:p><w:p w14:paraId="385906A5" w14:textId="77777777" w:rsidR="00D5346D" w:rsidRPr="00D5346D" w:rsidRDefault="00D5346D" w:rsidP="00D5346D"><w:pPr><w:numPr><w:ilvl w:val="0"/><w:numId w:val="8"/></w:numPr></w:pPr><w:r w:rsidRPr="00D5346D"><w:t>Employers</w:t></w:r></w:p><w:p w14:paraId="4A60CA52" w14:textId="77777777" w:rsidR="00D5346D" w:rsidRPr="00D5346D" w:rsidRDefault="00D5346D" w:rsidP="00D5346D"><w:pPr><w:numPr><w:ilvl w:val="0"/><w:numId w:val="8"/></w:numPr></w:pPr><w:r w:rsidRPr="00D5346D"><w:t>Payment processors (including NAEDO systems)</w:t></w:r></w:p><w:p w14:paraId="7E3E9895" w14:textId="77777777" w:rsidR="00D5346D" w:rsidRPr="00D5346D" w:rsidRDefault="00D5346D" w:rsidP="00D5346D"><w:pPr><w:numPr><w:ilvl w:val="0"/><w:numId w:val="8"/></w:numPr></w:pPr><w:r w:rsidRPr="00D5346D"><w:t>Debt collectors, attorneys, and tracing agents where necessary</w:t></w:r></w:p><w:p w14:paraId="42708271" w14:textId="77777777" w:rsidR="00D5346D" w:rsidRPr="00D5346D" w:rsidRDefault="00D5346D" w:rsidP="00D5346D"><w:r w:rsidRPr="00D5346D"><w:t>8.4 The Applicant acknowledges their rights to:</w:t></w:r></w:p><w:p w14:paraId="7148FBB2" w14:textId="77777777" w:rsidR="00D5346D" w:rsidRPr="00D5346D" w:rsidRDefault="00D5346D" w:rsidP="00D5346D"><w:pPr><w:numPr><w:ilvl w:val="0"/><w:numId w:val="9"/></w:numPr></w:pPr><w:r w:rsidRPr="00D5346D"><w:t>Access their personal information</w:t></w:r></w:p><w:p w14:paraId="17ECC2EB" w14:textId="77777777" w:rsidR="00D5346D" w:rsidRDefault="00D5346D" w:rsidP="00D5346D"><w:pPr><w:numPr><w:ilvl w:val="0"/><w:numId w:val="9"/></w:numPr></w:pPr><w:r w:rsidRPr="00D5346D"><w:t>Request correction or deletion where applicable</w:t></w:r></w:p><w:p w14:paraId="43BEA9F1" w14:textId="77777777" w:rsidR="00D21857" w:rsidRDefault="00D21857" w:rsidP="00D21857"/><w:p w14:paraId="3552E56F" w14:textId="77777777" w:rsidR="00D21857" w:rsidRPr="00D21857" w:rsidRDefault="00D21857" w:rsidP="00D21857"><w:pPr><w:rPr><w:b/><w:bCs/></w:rPr></w:pPr><w:r w:rsidRPr="00D21857"><w:rPr><w:b/><w:bCs/></w:rPr><w:t>8A. DATA RETENTION AND DELETION</w:t></w:r></w:p><w:p w14:paraId="483892DD" w14:textId="77777777" w:rsidR="00D21857" w:rsidRPr="00D21857" w:rsidRDefault="00D21857" w:rsidP="00D21857"><w:r w:rsidRPr="00D21857"><w:t>8A.1 The Credit Provider will retain the Applicant’s personal information only for as long as is necessary to fulfil the purposes for which it was collected, including but not limited to:</w:t></w:r></w:p><w:p w14:paraId="3D670353" w14:textId="77777777" w:rsidR="00D21857" w:rsidRPr="00D21857" w:rsidRDefault="00D21857" w:rsidP="00D21857"><w:pPr><w:numPr><w:ilvl w:val="0"/><w:numId w:val="23"/></w:numPr></w:pPr><w:r w:rsidRPr="00D21857"><w:t>The administration and enforcement of this Agreement</w:t></w:r></w:p><w:p w14:paraId="33F7553B" w14:textId="77777777" w:rsidR="00D21857" w:rsidRPr="00D21857" w:rsidRDefault="00D21857" w:rsidP="00D21857"><w:pPr><w:numPr><w:ilvl w:val="0"/><w:numId w:val="23"/></w:numPr></w:pPr><w:r w:rsidRPr="00D21857"><w:t>Compliance with legal and regulatory obligations</w:t></w:r></w:p><w:p w14:paraId="328D7640" w14:textId="77777777" w:rsidR="00D21857" w:rsidRPr="00D21857" w:rsidRDefault="00D21857" w:rsidP="00D21857"><w:pPr><w:numPr><w:ilvl w:val="0"/><w:numId w:val="23"/></w:numPr></w:pPr><w:r w:rsidRPr="00D21857"><w:t>Audit, accounting, and tax requirements</w:t></w:r></w:p><w:p w14:paraId="77FE4977" w14:textId="77777777" w:rsidR="00D21857" w:rsidRPr="00D21857" w:rsidRDefault="00D21857" w:rsidP="00D21857"><w:pPr><w:numPr><w:ilvl w:val="0"/><w:numId w:val="23"/></w:numPr></w:pPr><w:r w:rsidRPr="00D21857"><w:t>Fraud prevention and detection</w:t></w:r></w:p><w:p w14:paraId="715560B9" w14:textId="77777777" w:rsidR="00D21857" w:rsidRPr="00D21857" w:rsidRDefault="00D21857" w:rsidP="00D21857"><w:pPr><w:numPr><w:ilvl w:val="0"/><w:numId w:val="23"/></w:numPr></w:pPr><w:r w:rsidRPr="00D21857"><w:t>Resolving disputes and enforcing legal rights</w:t></w:r></w:p><w:p w14:paraId="736C9B34" w14:textId="77777777" w:rsidR="00D21857" w:rsidRPr="00D21857" w:rsidRDefault="00D21857" w:rsidP="00D21857"><w:r w:rsidRPr="00D21857"><w:t xml:space="preserve">8A.2 The Applicant acknowledges and agrees that the Credit Provider may be required to retain personal information for a period after the termination or settlement of this </w:t></w:r><w:r w:rsidRPr="00D21857"><w:lastRenderedPageBreak/><w:t>Agreement, as required by applicable law, including obligations under the National Credit Act and other applicable legislation.</w:t></w:r></w:p><w:p w14:paraId="288B1FCA" w14:textId="77777777" w:rsidR="00D21857" w:rsidRPr="00D21857" w:rsidRDefault="00D21857" w:rsidP="00D21857"><w:r w:rsidRPr="00D21857"><w:t>8A.3 The Applicant may request the correction, deletion, or restriction of their personal information. Such requests will be considered in accordance with applicable law.</w:t></w:r></w:p><w:p w14:paraId="7C4F52A2" w14:textId="77777777" w:rsidR="00D21857" w:rsidRPr="00D21857" w:rsidRDefault="00D21857" w:rsidP="00D21857"><w:r w:rsidRPr="00D21857"><w:t>8A.4 The Credit Provider reserves the right to decline a request for deletion where:</w:t></w:r></w:p><w:p w14:paraId="0A221148" w14:textId="77777777" w:rsidR="00D21857" w:rsidRPr="00D21857" w:rsidRDefault="00D21857" w:rsidP="00D21857"><w:pPr><w:numPr><w:ilvl w:val="0"/><w:numId w:val="24"/></w:numPr></w:pPr><w:r w:rsidRPr="00D21857"><w:t>The information is required to comply with a legal obligation</w:t></w:r></w:p><w:p w14:paraId="57FDB785" w14:textId="77777777" w:rsidR="00D21857" w:rsidRPr="00D21857" w:rsidRDefault="00D21857" w:rsidP="00D21857"><w:pPr><w:numPr><w:ilvl w:val="0"/><w:numId w:val="24"/></w:numPr></w:pPr><w:r w:rsidRPr="00D21857"><w:t>The information is required to establish, exercise, or defend a legal right</w:t></w:r></w:p><w:p w14:paraId="3B764448" w14:textId="77777777" w:rsidR="00D21857" w:rsidRPr="00D21857" w:rsidRDefault="00D21857" w:rsidP="00D21857"><w:pPr><w:numPr><w:ilvl w:val="0"/><w:numId w:val="24"/></w:numPr></w:pPr><w:r w:rsidRPr="00D21857"><w:t>The information is required for legitimate business purposes, including audit and record-keeping</w:t></w:r></w:p><w:p w14:paraId="43264543" w14:textId="77777777" w:rsidR="00D21857" w:rsidRPr="00D21857" w:rsidRDefault="00D21857" w:rsidP="00D21857"><w:r w:rsidRPr="00D21857"><w:t>8A.5 Where personal information is no longer required and no lawful basis for retention exists, the Credit Provider will take reasonable steps to:</w:t></w:r></w:p><w:p w14:paraId="2E3C03A4" w14:textId="77777777" w:rsidR="00D21857" w:rsidRPr="00D21857" w:rsidRDefault="00D21857" w:rsidP="00D21857"><w:pPr><w:numPr><w:ilvl w:val="0"/><w:numId w:val="25"/></w:numPr></w:pPr><w:r w:rsidRPr="00D21857"><w:t>Securely delete such information; or</w:t></w:r></w:p><w:p w14:paraId="4F647E6C" w14:textId="77777777" w:rsidR="00D21857" w:rsidRPr="00D21857" w:rsidRDefault="00D21857" w:rsidP="00D21857"><w:pPr><w:numPr><w:ilvl w:val="0"/><w:numId w:val="25"/></w:numPr></w:pPr><w:r w:rsidRPr="00D21857"><w:t>De-identify or anonymise the information</w:t></w:r></w:p><w:p w14:paraId="10477AC2" w14:textId="6566250D" w:rsidR="00D21857" w:rsidRPr="00D5346D" w:rsidRDefault="00D21857" w:rsidP="00D21857"><w:r w:rsidRPr="00D21857"><w:t>8A.6 The Credit Provider will implement appropriate technical and organisational measures to safeguard personal information against loss, unauthorised access, or unlawful processing.</w:t></w:r></w:p><w:p w14:paraId="70FE7088" w14:textId="77777777" w:rsidR="00D5346D" w:rsidRPr="00D5346D" w:rsidRDefault="00000000" w:rsidP="00D5346D"><w:r><w:pict w14:anchorId="6585DC3A"><v:rect id="_x0000_i1033" style="width:0;height:1.5pt" o:hralign="center" o:hrstd="t" o:hr="t" fillcolor="#a0a0a0" stroked="f"/></w:pict></w:r></w:p><w:p w14:paraId="6C301654" w14:textId="77777777" w:rsidR="00D5346D" w:rsidRPr="00D5346D" w:rsidRDefault="00D5346D" w:rsidP="00D5346D"><w:pPr><w:rPr><w:b/><w:bCs/></w:rPr></w:pPr><w:r w:rsidRPr="00D5346D"><w:rPr><w:b/><w:bCs/></w:rPr><w:t>9. ELECTRONIC COMMUNICATION AND SIGNATURE</w:t></w:r></w:p><w:p w14:paraId="0BD57759" w14:textId="77777777" w:rsidR="00D5346D" w:rsidRPr="00D5346D" w:rsidRDefault="00D5346D" w:rsidP="00D5346D"><w:r w:rsidRPr="00D5346D"><w:t>9.1 The Applicant agrees to receive all communication electronically via:</w:t></w:r></w:p><w:p w14:paraId="17505B4A" w14:textId="77777777" w:rsidR="00D5346D" w:rsidRPr="00D5346D" w:rsidRDefault="00D5346D" w:rsidP="00D5346D"><w:pPr><w:numPr><w:ilvl w:val="0"/><w:numId w:val="10"/></w:numPr></w:pPr><w:r w:rsidRPr="00D5346D"><w:t>Email</w:t></w:r></w:p><w:p w14:paraId="00CAE414" w14:textId="77777777" w:rsidR="00D5346D" w:rsidRPr="00D5346D" w:rsidRDefault="00D5346D" w:rsidP="00D5346D"><w:pPr><w:numPr><w:ilvl w:val="0"/><w:numId w:val="10"/></w:numPr></w:pPr><w:r w:rsidRPr="00D5346D"><w:t>SMS</w:t></w:r></w:p><w:p w14:paraId="029C7D9B" w14:textId="77777777" w:rsidR="00D5346D" w:rsidRPr="00D5346D" w:rsidRDefault="00D5346D" w:rsidP="00D5346D"><w:pPr><w:numPr><w:ilvl w:val="0"/><w:numId w:val="10"/></w:numPr></w:pPr><w:r w:rsidRPr="00D5346D"><w:t>LMS platform</w:t></w:r></w:p><w:p w14:paraId="488B4879" w14:textId="77777777" w:rsidR="00D5346D" w:rsidRPr="00D5346D" w:rsidRDefault="00D5346D" w:rsidP="00D5346D"><w:pPr><w:numPr><w:ilvl w:val="0"/><w:numId w:val="10"/></w:numPr></w:pPr><w:r w:rsidRPr="00D5346D"><w:t>WhatsApp or other digital channels</w:t></w:r></w:p><w:p w14:paraId="226832E5" w14:textId="77777777" w:rsidR="00D5346D" w:rsidRPr="00D5346D" w:rsidRDefault="00D5346D" w:rsidP="00D5346D"><w:r w:rsidRPr="00D5346D"><w:t>9.2 The Applicant consents that:</w:t></w:r></w:p><w:p w14:paraId="127539C2" w14:textId="77777777" w:rsidR="00D5346D" w:rsidRPr="00D5346D" w:rsidRDefault="00D5346D" w:rsidP="00D5346D"><w:pPr><w:numPr><w:ilvl w:val="0"/><w:numId w:val="11"/></w:numPr></w:pPr><w:r w:rsidRPr="00D5346D"><w:t>Electronic acceptance constitutes a legally binding signature</w:t></w:r></w:p><w:p w14:paraId="363594A7" w14:textId="77777777" w:rsidR="00D5346D" w:rsidRPr="00D5346D" w:rsidRDefault="00D5346D" w:rsidP="00D5346D"><w:pPr><w:numPr><w:ilvl w:val="0"/><w:numId w:val="11"/></w:numPr></w:pPr><w:r w:rsidRPr="00D5346D"><w:t>Documents delivered electronically are valid and enforceable</w:t></w:r></w:p><w:p w14:paraId="4094A7F4" w14:textId="77777777" w:rsidR="00D5346D" w:rsidRPr="00D5346D" w:rsidRDefault="00000000" w:rsidP="00D5346D"><w:r><w:pict w14:anchorId="5B5E8B5D"><v:rect id="_x0000_i1034" style="width:0;height:1.5pt" o:hralign="center" o:hrstd="t" o:hr="t" fillcolor="#a0a0a0" stroked="f"/></w:pict></w:r></w:p><w:p w14:paraId="21FC1AF4" w14:textId="77777777" w:rsidR="00D5346D" w:rsidRPr="00D5346D" w:rsidRDefault="00D5346D" w:rsidP="00D5346D"><w:pPr><w:rPr><w:b/><w:bCs/></w:rPr></w:pPr><w:r w:rsidRPr="00D5346D"><w:rPr><w:b/><w:bCs/></w:rPr><w:t>10. COMMUNICATION CONSENT</w:t></w:r></w:p><w:p w14:paraId="5FA2B7EA" w14:textId="77777777" w:rsidR="00D5346D" w:rsidRPr="00D5346D" w:rsidRDefault="00D5346D" w:rsidP="00D5346D"><w:r w:rsidRPr="00D5346D"><w:t>10.1 The Applicant consents to being contacted for:</w:t></w:r></w:p><w:p w14:paraId="00766B78" w14:textId="77777777" w:rsidR="00D5346D" w:rsidRPr="00D5346D" w:rsidRDefault="00D5346D" w:rsidP="00D5346D"><w:pPr><w:numPr><w:ilvl w:val="0"/><w:numId w:val="12"/></w:numPr></w:pPr><w:r w:rsidRPr="00D5346D"><w:t>Account administration and payment reminders</w:t></w:r></w:p><w:p w14:paraId="5A059DCE" w14:textId="77777777" w:rsidR="00D5346D" w:rsidRPr="00D5346D" w:rsidRDefault="00D5346D" w:rsidP="00D5346D"><w:pPr><w:numPr><w:ilvl w:val="0"/><w:numId w:val="12"/></w:numPr></w:pPr><w:r w:rsidRPr="00D5346D"><w:lastRenderedPageBreak/><w:t>Collections and recovery processes</w:t></w:r></w:p><w:p w14:paraId="2483BF0E" w14:textId="77777777" w:rsidR="00D5346D" w:rsidRPr="00D5346D" w:rsidRDefault="00D5346D" w:rsidP="00D5346D"><w:r w:rsidRPr="00D5346D"><w:t>10.2 Marketing communication will only be sent where separately consented to by the Applicant.</w:t></w:r></w:p><w:p w14:paraId="6D454B82" w14:textId="77777777" w:rsidR="00D5346D" w:rsidRPr="00D5346D" w:rsidRDefault="00000000" w:rsidP="00D5346D"><w:r><w:pict w14:anchorId="55155702"><v:rect id="_x0000_i1035" style="width:0;height:1.5pt" o:hralign="center" o:hrstd="t" o:hr="t" fillcolor="#a0a0a0" stroked="f"/></w:pict></w:r></w:p><w:p w14:paraId="166EA8C0" w14:textId="77777777" w:rsidR="00D5346D" w:rsidRPr="00D5346D" w:rsidRDefault="00D5346D" w:rsidP="00D5346D"><w:pPr><w:rPr><w:b/><w:bCs/></w:rPr></w:pPr><w:r w:rsidRPr="00D5346D"><w:rPr><w:b/><w:bCs/></w:rPr><w:t>11. COOLING-OFF PERIOD</w:t></w:r></w:p><w:p w14:paraId="2E4C7E3B" w14:textId="77777777" w:rsidR="00D5346D" w:rsidRPr="00D5346D" w:rsidRDefault="00D5346D" w:rsidP="00D5346D"><w:r w:rsidRPr="00D5346D"><w:t xml:space="preserve">11.1 The Applicant has the right to cancel this Agreement within </w:t></w:r><w:r w:rsidRPr="00D5346D"><w:rPr><w:b/><w:bCs/></w:rPr><w:t>5 (five) business days</w:t></w:r><w:r w:rsidRPr="00D5346D"><w:t xml:space="preserve"> of acceptance.</w:t></w:r></w:p><w:p w14:paraId="479364EA" w14:textId="77777777" w:rsidR="00D5346D" w:rsidRPr="00D5346D" w:rsidRDefault="00D5346D" w:rsidP="00D5346D"><w:r w:rsidRPr="00D5346D"><w:t>11.2 To cancel, the Applicant must:</w:t></w:r></w:p><w:p w14:paraId="7C9349C8" w14:textId="77777777" w:rsidR="00D5346D" w:rsidRPr="00D5346D" w:rsidRDefault="00D5346D" w:rsidP="00D5346D"><w:pPr><w:numPr><w:ilvl w:val="0"/><w:numId w:val="13"/></w:numPr></w:pPr><w:r w:rsidRPr="00D5346D"><w:t>Provide written notice, and</w:t></w:r></w:p><w:p w14:paraId="3982899F" w14:textId="77777777" w:rsidR="00D5346D" w:rsidRPr="00D5346D" w:rsidRDefault="00D5346D" w:rsidP="00D5346D"><w:pPr><w:numPr><w:ilvl w:val="0"/><w:numId w:val="13"/></w:numPr></w:pPr><w:r w:rsidRPr="00D5346D"><w:t>Repay the full loan amount received</w:t></w:r></w:p><w:p w14:paraId="5FE67E4A" w14:textId="77777777" w:rsidR="00D5346D" w:rsidRPr="00D5346D" w:rsidRDefault="00D5346D" w:rsidP="00D5346D"><w:r w:rsidRPr="00D5346D"><w:t>11.3 Interest and reasonable costs for the period the loan was used may apply.</w:t></w:r></w:p><w:p w14:paraId="2887BB72" w14:textId="77777777" w:rsidR="00D5346D" w:rsidRPr="00D5346D" w:rsidRDefault="00000000" w:rsidP="00D5346D"><w:r><w:pict w14:anchorId="2EB7DAF8"><v:rect id="_x0000_i1036" style="width:0;height:1.5pt" o:hralign="center" o:hrstd="t" o:hr="t" fillcolor="#a0a0a0" stroked="f"/></w:pict></w:r></w:p><w:p w14:paraId="7A2EC0BA" w14:textId="77777777" w:rsidR="00D5346D" w:rsidRPr="00D5346D" w:rsidRDefault="00D5346D" w:rsidP="00D5346D"><w:pPr><w:rPr><w:b/><w:bCs/></w:rPr></w:pPr><w:r w:rsidRPr="00D5346D"><w:rPr><w:b/><w:bCs/></w:rPr><w:t>12. SETTLEMENT</w:t></w:r></w:p><w:p w14:paraId="6EA4A83D" w14:textId="77777777" w:rsidR="00D5346D" w:rsidRPr="00D5346D" w:rsidRDefault="00D5346D" w:rsidP="00D5346D"><w:r w:rsidRPr="00D5346D"><w:t>12.1 The Applicant may settle the loan at any time.</w:t></w:r></w:p><w:p w14:paraId="3DD711FD" w14:textId="77777777" w:rsidR="00D5346D" w:rsidRPr="00D5346D" w:rsidRDefault="00D5346D" w:rsidP="00D5346D"><w:r w:rsidRPr="00D5346D"><w:t>12.2 The settlement amount will be:</w:t></w:r></w:p><w:p w14:paraId="7ED9EB0D" w14:textId="77777777" w:rsidR="00D5346D" w:rsidRPr="00D5346D" w:rsidRDefault="00D5346D" w:rsidP="00D5346D"><w:pPr><w:numPr><w:ilvl w:val="0"/><w:numId w:val="14"/></w:numPr></w:pPr><w:r w:rsidRPr="00D5346D"><w:t>Outstanding balance</w:t></w:r></w:p><w:p w14:paraId="091B5141" w14:textId="77777777" w:rsidR="00D5346D" w:rsidRPr="00D5346D" w:rsidRDefault="00D5346D" w:rsidP="00D5346D"><w:pPr><w:numPr><w:ilvl w:val="0"/><w:numId w:val="14"/></w:numPr></w:pPr><w:r w:rsidRPr="00D5346D"><w:t>Less any future interest and service fees not yet accrued</w:t></w:r></w:p><w:p w14:paraId="7808E415" w14:textId="77777777" w:rsidR="00D5346D" w:rsidRPr="00D5346D" w:rsidRDefault="00000000" w:rsidP="00D5346D"><w:r><w:pict w14:anchorId="5E581D81"><v:rect id="_x0000_i1037" style="width:0;height:1.5pt" o:hralign="center" o:hrstd="t" o:hr="t" fillcolor="#a0a0a0" stroked="f"/></w:pict></w:r></w:p><w:p w14:paraId="0822DFAF" w14:textId="77777777" w:rsidR="00D5346D" w:rsidRPr="00D5346D" w:rsidRDefault="00D5346D" w:rsidP="00D5346D"><w:pPr><w:rPr><w:b/><w:bCs/></w:rPr></w:pPr><w:r w:rsidRPr="00D5346D"><w:rPr><w:b/><w:bCs/></w:rPr><w:t>13. DEFAULT AND BREACH</w:t></w:r></w:p><w:p w14:paraId="3CEBFF56" w14:textId="77777777" w:rsidR="00D5346D" w:rsidRPr="00D5346D" w:rsidRDefault="00D5346D" w:rsidP="00D5346D"><w:r w:rsidRPr="00D5346D"><w:t>13.1 The Applicant will be in default if:</w:t></w:r></w:p><w:p w14:paraId="44AF5A03" w14:textId="77777777" w:rsidR="00D5346D" w:rsidRPr="00D5346D" w:rsidRDefault="00D5346D" w:rsidP="00D5346D"><w:pPr><w:numPr><w:ilvl w:val="0"/><w:numId w:val="15"/></w:numPr></w:pPr><w:r w:rsidRPr="00D5346D"><w:t>Payments are missed</w:t></w:r></w:p><w:p w14:paraId="161D01C7" w14:textId="77777777" w:rsidR="00D5346D" w:rsidRPr="00D5346D" w:rsidRDefault="00D5346D" w:rsidP="00D5346D"><w:pPr><w:numPr><w:ilvl w:val="0"/><w:numId w:val="15"/></w:numPr></w:pPr><w:r w:rsidRPr="00D5346D"><w:t>Any term of this Agreement is breached</w:t></w:r></w:p><w:p w14:paraId="71D9FD37" w14:textId="77777777" w:rsidR="00D5346D" w:rsidRPr="00D5346D" w:rsidRDefault="00D5346D" w:rsidP="00D5346D"><w:r w:rsidRPr="00D5346D"><w:t xml:space="preserve">13.2 The Credit Provider will issue a written notice allowing </w:t></w:r><w:r w:rsidRPr="00D5346D"><w:rPr><w:b/><w:bCs/></w:rPr><w:t>at least 20 business days</w:t></w:r><w:r w:rsidRPr="00D5346D"><w:t xml:space="preserve"> to remedy the default.</w:t></w:r></w:p><w:p w14:paraId="52D42396" w14:textId="77777777" w:rsidR="00D5346D" w:rsidRPr="00D5346D" w:rsidRDefault="00D5346D" w:rsidP="00D5346D"><w:r w:rsidRPr="00D5346D"><w:t>13.3 The notice will inform the Applicant of their rights, including:</w:t></w:r></w:p><w:p w14:paraId="2F660E08" w14:textId="77777777" w:rsidR="00D5346D" w:rsidRPr="00D5346D" w:rsidRDefault="00D5346D" w:rsidP="00D5346D"><w:pPr><w:numPr><w:ilvl w:val="0"/><w:numId w:val="16"/></w:numPr></w:pPr><w:r w:rsidRPr="00D5346D"><w:t>Referring the matter to a debt counsellor</w:t></w:r></w:p><w:p w14:paraId="793508E4" w14:textId="77777777" w:rsidR="00D5346D" w:rsidRPr="00D5346D" w:rsidRDefault="00D5346D" w:rsidP="00D5346D"><w:pPr><w:numPr><w:ilvl w:val="0"/><w:numId w:val="16"/></w:numPr></w:pPr><w:r w:rsidRPr="00D5346D"><w:t>Alternative dispute resolution</w:t></w:r></w:p><w:p w14:paraId="02A317AE" w14:textId="77777777" w:rsidR="00D5346D" w:rsidRPr="00D5346D" w:rsidRDefault="00000000" w:rsidP="00D5346D"><w:r><w:pict w14:anchorId="7570CDA7"><v:rect id="_x0000_i1038" style="width:0;height:1.5pt" o:hralign="center" o:hrstd="t" o:hr="t" fillcolor="#a0a0a0" stroked="f"/></w:pict></w:r></w:p><w:p w14:paraId="45D023A3" w14:textId="77777777" w:rsidR="00D5346D" w:rsidRPr="00D5346D" w:rsidRDefault="00D5346D" w:rsidP="00D5346D"><w:pPr><w:rPr><w:b/><w:bCs/></w:rPr></w:pPr><w:r w:rsidRPr="00D5346D"><w:rPr><w:b/><w:bCs/></w:rPr><w:t>14. LEGAL ENFORCEMENT</w:t></w:r></w:p><w:p w14:paraId="5CF3EB3F" w14:textId="77777777" w:rsidR="00D5346D" w:rsidRPr="00D5346D" w:rsidRDefault="00D5346D" w:rsidP="00D5346D"><w:r w:rsidRPr="00D5346D"><w:lastRenderedPageBreak/><w:t>14.1 If the Applicant fails to remedy the default, the Credit Provider may:</w:t></w:r></w:p><w:p w14:paraId="1494C839" w14:textId="77777777" w:rsidR="00D5346D" w:rsidRPr="00D5346D" w:rsidRDefault="00D5346D" w:rsidP="00D5346D"><w:pPr><w:numPr><w:ilvl w:val="0"/><w:numId w:val="17"/></w:numPr></w:pPr><w:r w:rsidRPr="00D5346D"><w:t>Demand full outstanding balance</w:t></w:r></w:p><w:p w14:paraId="2AD2019C" w14:textId="77777777" w:rsidR="00D5346D" w:rsidRPr="00D5346D" w:rsidRDefault="00D5346D" w:rsidP="00D5346D"><w:pPr><w:numPr><w:ilvl w:val="0"/><w:numId w:val="17"/></w:numPr></w:pPr><w:r w:rsidRPr="00D5346D"><w:t>Cancel the Agreement</w:t></w:r></w:p><w:p w14:paraId="55947B69" w14:textId="77777777" w:rsidR="00D5346D" w:rsidRPr="00D5346D" w:rsidRDefault="00D5346D" w:rsidP="00D5346D"><w:pPr><w:numPr><w:ilvl w:val="0"/><w:numId w:val="17"/></w:numPr></w:pPr><w:r w:rsidRPr="00D5346D"><w:t>Institute legal proceedings</w:t></w:r></w:p><w:p w14:paraId="3C4F5EC2" w14:textId="77777777" w:rsidR="00D5346D" w:rsidRPr="00D5346D" w:rsidRDefault="00D5346D" w:rsidP="00D5346D"><w:r w:rsidRPr="00D5346D"><w:t>14.2 The Applicant agrees to the jurisdiction of the Magistrate’s Court.</w:t></w:r></w:p><w:p w14:paraId="4BF31CBB" w14:textId="77777777" w:rsidR="00D5346D" w:rsidRPr="00D5346D" w:rsidRDefault="00D5346D" w:rsidP="00D5346D"><w:r w:rsidRPr="00D5346D"><w:t>14.3 The Applicant will be liable for reasonable legal and collection costs as permitted by law.</w:t></w:r></w:p><w:p w14:paraId="48A20D1F" w14:textId="77777777" w:rsidR="00D5346D" w:rsidRPr="00D5346D" w:rsidRDefault="00000000" w:rsidP="00D5346D"><w:r><w:pict w14:anchorId="038E802D"><v:rect id="_x0000_i1039" style="width:0;height:1.5pt" o:hralign="center" o:hrstd="t" o:hr="t" fillcolor="#a0a0a0" stroked="f"/></w:pict></w:r></w:p><w:p w14:paraId="0BDE3A47" w14:textId="77777777" w:rsidR="00D5346D" w:rsidRPr="00D5346D" w:rsidRDefault="00D5346D" w:rsidP="00D5346D"><w:pPr><w:rPr><w:b/><w:bCs/></w:rPr></w:pPr><w:r w:rsidRPr="00D5346D"><w:rPr><w:b/><w:bCs/></w:rPr><w:t>15. TRACING AND COLLECTIONS</w:t></w:r></w:p><w:p w14:paraId="676E6B5D" w14:textId="77777777" w:rsidR="00D5346D" w:rsidRPr="00D5346D" w:rsidRDefault="00D5346D" w:rsidP="00D5346D"><w:r w:rsidRPr="00D5346D"><w:t>15.1 The Applicant consents to:</w:t></w:r></w:p><w:p w14:paraId="1219CA1F" w14:textId="77777777" w:rsidR="00D5346D" w:rsidRPr="00D5346D" w:rsidRDefault="00D5346D" w:rsidP="00D5346D"><w:pPr><w:numPr><w:ilvl w:val="0"/><w:numId w:val="18"/></w:numPr></w:pPr><w:r w:rsidRPr="00D5346D"><w:t>Tracing via NAEDO systems</w:t></w:r></w:p><w:p w14:paraId="026BB9FE" w14:textId="77777777" w:rsidR="00D5346D" w:rsidRPr="00D5346D" w:rsidRDefault="00D5346D" w:rsidP="00D5346D"><w:pPr><w:numPr><w:ilvl w:val="0"/><w:numId w:val="18"/></w:numPr></w:pPr><w:r w:rsidRPr="00D5346D"><w:t>Use of third-party tracing agents if contact is lost</w:t></w:r></w:p><w:p w14:paraId="79CAF79F" w14:textId="77777777" w:rsidR="00D5346D" w:rsidRPr="00D5346D" w:rsidRDefault="00000000" w:rsidP="00D5346D"><w:r><w:pict w14:anchorId="0CD7DF3F"><v:rect id="_x0000_i1040" style="width:0;height:1.5pt" o:hralign="center" o:hrstd="t" o:hr="t" fillcolor="#a0a0a0" stroked="f"/></w:pict></w:r></w:p><w:p w14:paraId="7A8A915C" w14:textId="77777777" w:rsidR="00D5346D" w:rsidRPr="00D5346D" w:rsidRDefault="00D5346D" w:rsidP="00D5346D"><w:pPr><w:rPr><w:b/><w:bCs/></w:rPr></w:pPr><w:r w:rsidRPr="00D5346D"><w:rPr><w:b/><w:bCs/></w:rPr><w:t>16. ADDRESS FOR SERVICE</w:t></w:r></w:p><w:p w14:paraId="30F77E45" w14:textId="77777777" w:rsidR="00D5346D" w:rsidRPr="00D5346D" w:rsidRDefault="00D5346D" w:rsidP="00D5346D"><w:r w:rsidRPr="00D5346D"><w:t xml:space="preserve">16.1 The parties choose their provided addresses as </w:t></w:r><w:proofErr w:type="spellStart"/><w:r w:rsidRPr="00D5346D"><w:t>domicilium</w:t></w:r><w:proofErr w:type="spellEnd"/><w:r w:rsidRPr="00D5346D"><w:t xml:space="preserve"> </w:t></w:r><w:proofErr w:type="spellStart"/><w:r w:rsidRPr="00D5346D"><w:t>citandi</w:t></w:r><w:proofErr w:type="spellEnd"/><w:r w:rsidRPr="00D5346D"><w:t xml:space="preserve"> et </w:t></w:r><w:proofErr w:type="spellStart"/><w:r w:rsidRPr="00D5346D"><w:t>executandi</w:t></w:r><w:proofErr w:type="spellEnd"/><w:r w:rsidRPr="00D5346D"><w:t>.</w:t></w:r></w:p><w:p w14:paraId="21B3DCAF" w14:textId="77777777" w:rsidR="00D5346D" w:rsidRPr="00D5346D" w:rsidRDefault="00D5346D" w:rsidP="00D5346D"><w:r w:rsidRPr="00D5346D"><w:t>16.2 Changes must be communicated in writing via:</w:t></w:r></w:p><w:p w14:paraId="0C25E138" w14:textId="77777777" w:rsidR="00D5346D" w:rsidRPr="00D5346D" w:rsidRDefault="00D5346D" w:rsidP="00D5346D"><w:pPr><w:numPr><w:ilvl w:val="0"/><w:numId w:val="19"/></w:numPr></w:pPr><w:r w:rsidRPr="00D5346D"><w:t>LMS</w:t></w:r></w:p><w:p w14:paraId="243DEB4D" w14:textId="77777777" w:rsidR="00D5346D" w:rsidRPr="00D5346D" w:rsidRDefault="00D5346D" w:rsidP="00D5346D"><w:pPr><w:numPr><w:ilvl w:val="0"/><w:numId w:val="19"/></w:numPr></w:pPr><w:r w:rsidRPr="00D5346D"><w:t>Email</w:t></w:r></w:p><w:p w14:paraId="7678A729" w14:textId="77777777" w:rsidR="00D5346D" w:rsidRPr="00D5346D" w:rsidRDefault="00D5346D" w:rsidP="00D5346D"><w:pPr><w:numPr><w:ilvl w:val="0"/><w:numId w:val="19"/></w:numPr></w:pPr><w:r w:rsidRPr="00D5346D"><w:t>Registered mail</w:t></w:r></w:p><w:p w14:paraId="0DB1C6F6" w14:textId="77777777" w:rsidR="00D5346D" w:rsidRPr="00D5346D" w:rsidRDefault="00000000" w:rsidP="00D5346D"><w:r><w:pict w14:anchorId="509C1D65"><v:rect id="_x0000_i1041" style="width:0;height:1.5pt" o:hralign="center" o:hrstd="t" o:hr="t" fillcolor="#a0a0a0" stroked="f"/></w:pict></w:r></w:p><w:p w14:paraId="782A709A" w14:textId="77777777" w:rsidR="00D5346D" w:rsidRPr="00D5346D" w:rsidRDefault="00D5346D" w:rsidP="00D5346D"><w:pPr><w:rPr><w:b/><w:bCs/></w:rPr></w:pPr><w:r w:rsidRPr="00D5346D"><w:rPr><w:b/><w:bCs/></w:rPr><w:t>17. TERMINATION</w:t></w:r></w:p><w:p w14:paraId="0F2ECEB7" w14:textId="77777777" w:rsidR="00D5346D" w:rsidRPr="00D5346D" w:rsidRDefault="00D5346D" w:rsidP="00D5346D"><w:r w:rsidRPr="00D5346D"><w:t>17.1 This Agreement terminates when:</w:t></w:r></w:p><w:p w14:paraId="11BD053F" w14:textId="77777777" w:rsidR="00D5346D" w:rsidRPr="00D5346D" w:rsidRDefault="00D5346D" w:rsidP="00D5346D"><w:pPr><w:numPr><w:ilvl w:val="0"/><w:numId w:val="20"/></w:numPr></w:pPr><w:r w:rsidRPr="00D5346D"><w:t>The loan is fully settled, or</w:t></w:r></w:p><w:p w14:paraId="1B7EEF4C" w14:textId="77777777" w:rsidR="00D5346D" w:rsidRPr="00D5346D" w:rsidRDefault="00D5346D" w:rsidP="00D5346D"><w:pPr><w:numPr><w:ilvl w:val="0"/><w:numId w:val="20"/></w:numPr></w:pPr><w:r w:rsidRPr="00D5346D"><w:t>It is lawfully cancelled</w:t></w:r></w:p><w:p w14:paraId="6FAEECEE" w14:textId="77777777" w:rsidR="00D5346D" w:rsidRPr="00D5346D" w:rsidRDefault="00000000" w:rsidP="00D5346D"><w:r><w:pict w14:anchorId="10209DA9"><v:rect id="_x0000_i1042" style="width:0;height:1.5pt" o:hralign="center" o:hrstd="t" o:hr="t" fillcolor="#a0a0a0" stroked="f"/></w:pict></w:r></w:p><w:p w14:paraId="24C45AC0" w14:textId="77777777" w:rsidR="00D5346D" w:rsidRPr="00D5346D" w:rsidRDefault="00D5346D" w:rsidP="00D5346D"><w:pPr><w:rPr><w:b/><w:bCs/></w:rPr></w:pPr><w:r w:rsidRPr="00D5346D"><w:rPr><w:b/><w:bCs/></w:rPr><w:t>18. GENERAL</w:t></w:r></w:p><w:p w14:paraId="1BDA4DFF" w14:textId="77777777" w:rsidR="00D5346D" w:rsidRPr="00D5346D" w:rsidRDefault="00D5346D" w:rsidP="00D5346D"><w:r w:rsidRPr="00D5346D"><w:t>18.1 This Agreement constitutes the entire agreement between the parties.</w:t></w:r></w:p><w:p w14:paraId="20EEE5BD" w14:textId="77777777" w:rsidR="00D5346D" w:rsidRPr="00D5346D" w:rsidRDefault="00D5346D" w:rsidP="00D5346D"><w:r w:rsidRPr="00D5346D"><w:t>18.2 Any amendments must be in writing.</w:t></w:r></w:p><w:p w14:paraId="07F03CAF" w14:textId="77777777" w:rsidR="00D5346D" w:rsidRPr="00D5346D" w:rsidRDefault="00D5346D" w:rsidP="00D5346D"><w:r w:rsidRPr="00D5346D"><w:lastRenderedPageBreak/><w:t>18.3 If any clause is found invalid, the remaining clauses remain enforceable.</w:t></w:r></w:p><w:p w14:paraId="2654C1D2" w14:textId="77777777" w:rsidR="00D5346D" w:rsidRPr="00D5346D" w:rsidRDefault="00000000" w:rsidP="00D5346D"><w:r><w:pict w14:anchorId="4E4D1A6F"><v:rect id="_x0000_i1043" style="width:0;height:1.5pt" o:hralign="center" o:hrstd="t" o:hr="t" fillcolor="#a0a0a0" stroked="f"/></w:pict></w:r></w:p><w:p w14:paraId="1C9C4A44" w14:textId="77777777" w:rsidR="00D5346D" w:rsidRPr="00D5346D" w:rsidRDefault="00D5346D" w:rsidP="00D5346D"><w:pPr><w:rPr><w:b/><w:bCs/></w:rPr></w:pPr><w:r w:rsidRPr="00D5346D"><w:rPr><w:b/><w:bCs/></w:rPr><w:t>19. ACKNOWLEDGEMENT OF RISK</w:t></w:r></w:p><w:p w14:paraId="32D9D64A" w14:textId="77777777" w:rsidR="00D5346D" w:rsidRPr="00D5346D" w:rsidRDefault="00D5346D" w:rsidP="00D5346D"><w:r w:rsidRPr="00D5346D"><w:t>19.1 The Applicant acknowledges that:</w:t></w:r></w:p><w:p w14:paraId="69FEA893" w14:textId="77777777" w:rsidR="00D5346D" w:rsidRPr="00D5346D" w:rsidRDefault="00D5346D" w:rsidP="00D5346D"><w:pPr><w:numPr><w:ilvl w:val="0"/><w:numId w:val="21"/></w:numPr></w:pPr><w:r w:rsidRPr="00D5346D"><w:t>Credit carries financial obligations and risks</w:t></w:r></w:p><w:p w14:paraId="69960B7B" w14:textId="77777777" w:rsidR="00D5346D" w:rsidRPr="00D5346D" w:rsidRDefault="00D5346D" w:rsidP="00D5346D"><w:pPr><w:numPr><w:ilvl w:val="0"/><w:numId w:val="21"/></w:numPr></w:pPr><w:r w:rsidRPr="00D5346D"><w:t>Failure to repay may negatively impact their credit profile and financial position</w:t></w:r></w:p><w:p w14:paraId="3C436618" w14:textId="77777777" w:rsidR="00D5346D" w:rsidRPr="00D5346D" w:rsidRDefault="00000000" w:rsidP="00D5346D"><w:r><w:pict w14:anchorId="7EFBFD72"><v:rect id="_x0000_i1044" style="width:0;height:1.5pt" o:hralign="center" o:hrstd="t" o:hr="t" fillcolor="#a0a0a0" stroked="f"/></w:pict></w:r></w:p><w:p w14:paraId="00B07C97" w14:textId="77777777" w:rsidR="00D5346D" w:rsidRPr="00D5346D" w:rsidRDefault="00D5346D" w:rsidP="00D5346D"><w:pPr><w:rPr><w:b/><w:bCs/></w:rPr></w:pPr><w:r w:rsidRPr="00D5346D"><w:rPr><w:b/><w:bCs/></w:rPr><w:t>20. ACCEPTANCE</w:t></w:r></w:p><w:p w14:paraId="0DA8667B" w14:textId="77777777" w:rsidR="00D5346D" w:rsidRPr="00D5346D" w:rsidRDefault="00D5346D" w:rsidP="00D5346D"><w:r w:rsidRPr="00D5346D"><w:t>By accepting this Agreement, the Applicant confirms that they:</w:t></w:r></w:p><w:p w14:paraId="107023F3" w14:textId="77777777" w:rsidR="00D5346D" w:rsidRPr="00D5346D" w:rsidRDefault="00D5346D" w:rsidP="00D5346D"><w:pPr><w:numPr><w:ilvl w:val="0"/><w:numId w:val="22"/></w:numPr></w:pPr><w:r w:rsidRPr="00D5346D"><w:t>Have read and understood all terms</w:t></w:r></w:p><w:p w14:paraId="391FE726" w14:textId="77777777" w:rsidR="00D5346D" w:rsidRPr="00D5346D" w:rsidRDefault="00D5346D" w:rsidP="00D5346D"><w:pPr><w:numPr><w:ilvl w:val="0"/><w:numId w:val="22"/></w:numPr></w:pPr><w:r w:rsidRPr="00D5346D"><w:t>Agree to be bound by this Agreement</w:t></w:r></w:p><w:p w14:paraId="17F3720A" w14:textId="77777777" w:rsidR="00D5346D" w:rsidRPr="00D5346D" w:rsidRDefault="00D5346D" w:rsidP="00D5346D"><w:pPr><w:numPr><w:ilvl w:val="0"/><w:numId w:val="22"/></w:numPr></w:pPr><w:r w:rsidRPr="00D5346D"><w:t>Consent to all authorisations contained herein</w:t></w:r></w:p><w:p w14:paraId="716AA187" w14:textId="77777777" w:rsidR="00D5346D" w:rsidRPr="00D5346D" w:rsidRDefault="00000000" w:rsidP="00D5346D"><w:r><w:pict w14:anchorId="2436F88D"><v:rect id="_x0000_i1045" style="width:0;height:1.5pt" o:hralign="center" o:hrstd="t" o:hr="t" fillcolor="#a0a0a0" stroked="f"/></w:pict></w:r></w:p><w:p w14:paraId="22C3A537" w14:textId="77777777" w:rsidR="00D5346D" w:rsidRPr="00D5346D" w:rsidRDefault="00D5346D" w:rsidP="00D5346D"><w:r w:rsidRPr="00D5346D"><w:rPr><w:b/><w:bCs/></w:rPr><w:t>END OF AGREEMENT</w:t></w:r></w:p><w:p w14:paraId="7333CE6C" w14:textId="77777777" w:rsidR="00D5346D" w:rsidRDefault="00D5346D"/><w:sectPr w:rsidR="00D5346D"><w:pgSz w:w="11906" w:h="16838"/><w:pgMar w:top="1440" w:right="1440" w:bottom="1440" w:left="1440" w:header="708" w:footer="708" w:gutter="0"/><w:cols w:space="708"/><w:docGrid w:linePitch="360"/></w:sectPr></w:body></w:document>